pipui/__init__.py
pipui/__main__.py
pipui/server.py
pipui/utils.py
pipui/templates/index.html
pipui-0.2.2.dist-info/METADATA
pipui-0.2.2.dist-info/WHEEL
pipui-0.2.2.dist-info/entry_points.txt
pipui-0.2.2.dist-info/top_level.txt
pipui-0.2.2.dist-info/RECORD
