Metadata-Version: 2.1
Name: pipui
Version: 0.2.2
Summary: A simple Python package management tool
Home-page: https://github.com/merlons/pipui.git
Author: merlon
License: BSD
Classifier: Programming Language :: Python :: 3
Classifier: Programming Language :: Python :: 3.6
Classifier: Programming Language :: Python :: 3.7
Classifier: Programming Language :: Python :: 3.8
Classifier: Programming Language :: Python :: 3.9
Classifier: License :: OSI Approved :: BSD License
Classifier: Operating System :: OS Independent
Requires-Python: >=3.6, <4
Requires-Dist: flask
Requires-Dist: beautifulsoup4
Requires-Dist: requests
